Stackem/ContStacker.py
Stackem/LineStacker.py
Stackem/__init__.py
Stackem/utils.py
Stackem/main.py
stackem-0.1.1.dist-info/RECORD
stackem-0.1.1.dist-info/METADATA
stackem-0.1.1.dist-info/top_level.txt
stackem-0.1.1.dist-info/metadata.json
stackem-0.1.1.dist-info/DESCRIPTION.rst
stackem-0.1.1.dist-info/WHEEL
stackem-0.1.1.data/scripts/stackem
