Metadata-Version: 2.0
Name: stackem
Version: 0.1.1
Summary: Image plane stacking tools.
Home-page: https://github.com/sphemakh/Stackem
Author: Sphesihle Makhathini
Author-email: Sphesihle Makhathini <sphemakh@gmail.com>
License: This program should come with the GNU General Public Licence. If not, find it at http://www.gnu.org/licenses/old-licenses/gpl-2.0-standalone.html
Platform: UNKNOWN
Requires: numpy
Requires: matplotlib
Requires: scipy
Requires: astLib
Requires: pyfits
